__init__.py
spacedata/__init__.py
spacedata/client.py
spacedata/downloader.py
spacedata/exceptions.py
spacedata/generators.py
spacedata/logger.py
spacedata/settings.py
spacedata/utils.py
spacedata/cache/__init__.py
spacedata/cache/base.py
spacedata/cache/duckdb_controller.py
spacedata/cache/memory_controller.py
spacedata/cache/setup.py
spacedata/decorators/__init__.py
spacedata/decorators/api_resource_exceptions.py
spacedata/decorators/api_resource_params.py
spacedata/decorators/api_resource_pipeline.py
spacedata/decorators/sdk_exceptions.py
spacedata/models/__init__.py
spacedata/models/apod.py
spacedata/models/donki.py
spacedata/models/insight.py
spacedata/models/neo.py
spacedata/resources/__init__.py
spacedata/resources/base.py
spacedata/resources/protocol.py
spacedata/resources/donki/__init__.py
spacedata/resources/donki/cme.py
spacedata/resources/donki/cme_analysis.py
spacedata/resources/donki/flr.py
spacedata/resources/donki/gst.py
spacedata/resources/donki/hss.py
spacedata/resources/donki/ips.py
spacedata/resources/donki/mpc.py
spacedata/resources/donki/notifications.py
spacedata/resources/donki/rbe.py
spacedata/resources/donki/sep.py
spacedata/resources/donki/wsa.py
spacedata/resources/insight/__init__.py
spacedata/resources/insight/weather.py
spacedata/resources/neo/__init__.py
spacedata/resources/neo/browse.py
spacedata/resources/neo/feed.py
spacedata/resources/neo/lookup.py
spacedata/resources/planetary/__init__.py
spacedata/resources/planetary/apod.py
spacedata/result/__init__.py
spacedata/result/base.py
spacedata/result/download_result.py
spacedata/result/pandas_result.py
spacedata/result/polars_result.py
spacedata/result/pyarrow_result.py
spacedata-0.1.1.dist-info/licenses/LICENSE
spacedata-0.1.1.dist-info/METADATA
spacedata-0.1.1.dist-info/WHEEL
spacedata-0.1.1.dist-info/top_level.txt
spacedata-0.1.1.dist-info/RECORD
