Metadata-Version: 2.4
Name: spacedata
Version: 0.1.1
Summary: A Python package to interact with NASA's services
Author-email: Alberto Daniel Badia <alberto_badia@enlacepatagonia.com>
Project-URL: Homepage, https://github.com/albertobadia/spacedata
Requires-Python: >=3.10
License-File: LICENSE
Requires-Dist: httpx>=0.28.1
Requires-Dist: parfive>=2.2.0
Requires-Dist: pydantic>=2.12.5
Requires-Dist: pydantic-settings>=2.12.0
Requires-Dist: tenacity>=9.1.2
Provides-Extra: duckdb
Requires-Dist: duckdb>=1.4.3; extra == "duckdb"
Provides-Extra: polars
Requires-Dist: polars-lts-cpu>=1.33.1; extra == "polars"
Provides-Extra: pandas
Requires-Dist: pandas>=2.3.3; extra == "pandas"
Provides-Extra: pyarrow
Requires-Dist: pyarrow>=22.0.0; extra == "pyarrow"
Dynamic: license-file
